ezFutures/__init__.py
ezFutures/ezFutures.py
ezFutures/utils.py
ezFutures/core/__init__.py
ezFutures/core/concurrent_futures_process_pool.py
ezFutures/core/managed_processes.py
ezFutures-0.0b21.dist-info/LICENSE
ezFutures-0.0b21.dist-info/METADATA
ezFutures-0.0b21.dist-info/WHEEL
ezFutures-0.0b21.dist-info/top_level.txt
ezFutures-0.0b21.dist-info/RECORD
