Metadata-Version: 2.1
Name: ezFutures
Version: 0.0b21
Summary: Parallism made easy (and safe) with futures API
Home-page: https://github.com/mozjay0619/ezFutures
Author: Jay Kim
License: DSB 3-clause
Platform: UNKNOWN
